setup.py
CIM/CIMReader.py
CIM/Contingency.py
CIM/ControlArea.py
CIM/Core.py
CIM/DesktopMenu.py
CIM/DesktopViewModel.py
CIM/Domain.py
CIM/Equivalents.py
CIM/LoadModel.py
CIM/Meas.py
CIM/Mixin.py
CIM/OperationalLimits.py
CIM/Outage.py
CIM/Protection.py
CIM/RDFXML.py
CIM/SCADA.py
CIM/Topology.py
CIM/ViewModel.py
CIM/Wires.py
CIM/__init__.py
CIM.egg-info/PKG-INFO
CIM.egg-info/SOURCES.txt
CIM.egg-info/dependency_links.txt
CIM.egg-info/entry_points.txt
CIM.egg-info/not-zip-safe
CIM.egg-info/requires.txt
CIM.egg-info/top_level.txt
CIM/Generation/GenerationDynamics.py
CIM/Generation/Production.py
CIM/Generation/__init__.py
CIM/Plugin/CIMPerspective.py
CIM/Plugin/CIMPlugin.py
CIM/Plugin/CIMWizard.py
CIM/Plugin/EditorExtension.py
CIM/Plugin/GraphEditor.py
CIM/Plugin/ImportWizard.py
CIM/Plugin/Run.py
CIM/Plugin/TreeEditor.py
CIM/Plugin/WizardExtension.py
CIM/Plugin/__init__.py
CIM/Test/AdapterTestCase.py
CIM/Test/CIMTestCase.py
CIM/Test/TreeNodeTestCase.py
CIM/Test/__init__.py
CIM13r19/Contingency.py
CIM13r19/ControlArea.py
CIM13r19/Core.py
CIM13r19/Domain.py
CIM13r19/Equivalents.py
CIM13r19/LoadModel.py
CIM13r19/Meas.py
CIM13r19/OperationalLimits.py
CIM13r19/Outage.py
CIM13r19/Protection.py
CIM13r19/SCADA.py
CIM13r19/Topology.py
CIM13r19/Wires.py
CIM13r19/__init__.py
CIM13r19/Generation/GenerationDynamics.py
CIM13r19/Generation/Production.py
CIM13r19/Generation/__init__.py
model/__init__.py