Metadata-Version: 1.0
Name: CIM
Version: 13.19.1
Summary: Python implementation of the Common Information Model.
Home-page: http://rwl.github.com/cim
Author: Richard W. Lincoln
Author-email: r.w.lincoln@gmail.com
License: GPLv2
Platform: UNKNOWN
